captain_cookie/__init__.py
captain_cookie/__main__.py
captain_cookie/cli.py
captain_cookie/templates/default/cookiecutter.json
captain_cookie/templates/default/hooks/post_gen_project.py
captain_cookie/templates/default/hooks/pre_gen_project.py
captain_cookie/templates/default/{{cookiecutter.project_slug}}/.gitignore
captain_cookie/templates/default/{{cookiecutter.project_slug}}/.gitlab-ci.yml
captain_cookie/templates/default/{{cookiecutter.project_slug}}/.gitpod.Dockerfile
captain_cookie/templates/default/{{cookiecutter.project_slug}}/.gitpod.yml
captain_cookie/templates/default/{{cookiecutter.project_slug}}/.pre-commit-config.yaml
captain_cookie/templates/default/{{cookiecutter.project_slug}}/.vscode/settings.json
captain_cookie/templates/default/{{cookiecutter.project_slug}}/README.md
captain_cookie/templates/default/{{cookiecutter.project_slug}}/ci/Dockerfile
captain_cookie/templates/default/{{cookiecutter.project_slug}}/docs/apidoc/index.md
captain_cookie/templates/default/{{cookiecutter.project_slug}}/docs/contributing/setup.md
captain_cookie/templates/default/{{cookiecutter.project_slug}}/docs/contributing/workflow.md
captain_cookie/templates/default/{{cookiecutter.project_slug}}/docs/css/custom.css
captain_cookie/templates/default/{{cookiecutter.project_slug}}/docs/css/termynal.css
captain_cookie/templates/default/{{cookiecutter.project_slug}}/docs/index.md
captain_cookie/templates/default/{{cookiecutter.project_slug}}/docs/js/custom.js
captain_cookie/templates/default/{{cookiecutter.project_slug}}/docs/js/termynal.js
captain_cookie/templates/default/{{cookiecutter.project_slug}}/docs/release-notes.md
captain_cookie/templates/default/{{cookiecutter.project_slug}}/mkdocs.yml
captain_cookie/templates/default/{{cookiecutter.project_slug}}/notebooks/.gitkeep
captain_cookie/templates/default/{{cookiecutter.project_slug}}/pyproject.toml
captain_cookie/templates/default/{{cookiecutter.project_slug}}/setup.cfg
captain_cookie-0.6.0.dist-info/entry_points.txt
captain_cookie-0.6.0.dist-info/WHEEL
captain_cookie-0.6.0.dist-info/METADATA
captain_cookie-0.6.0.dist-info/RECORD
